<markers>
<marker lat="38.966" lon="-78.4" site="Fishers Hill (Virginia, United States)"/>
<marker lat="33.733" lon="-84.383" site="Atlanta (Georgia, United States)"/>
<marker lat="39.933" lon="-77.65" site="Chambersburg, Pa. (Pennsylvania, United States)"/>
<marker lat="37.0" lon="-78.683" site="Charlotte county (Virginia, United States)"/>
<marker lat="37.4" lon="-77.3" site="Deep Bottom (Virginia, United States)"/>
<marker lat="34.933" lon="-79.766" site="Rockingham, N. C. (North Carolina, United States)"/>
<marker lat="32.7" lon="-79.883" site="Morris Island (South Carolina, United States)"/>
<marker lat="36.15" lon="-82.816" site="Greenville, Tenn. (Tennessee, United States)"/>
<marker lat="42.883" lon="-78.866" site="Buffalo, N. Y. (New York, United States)"/>
<marker lat="32.216" lon="-80.666" site="Hilton Head (South Carolina, United States)"/>
<marker lat="38.283" lon="-78.8" site="Port Republic (Virginia, United States)"/>
<marker lat="38.66" lon="-78.883" site="Waynesboro, Va. (Virginia, United States)"/>
<marker lat="37.516" lon="-77.383" site="Rocketts (Virginia, United States)"/>
<marker lat="38.0" lon="-98.0" site="United States (United States)"/>
<marker lat="60.0" lon="-96.0" site="Canada (Canada)"/>
<marker lat="35.5" lon="-80.0" site="North Carolina (North Carolina, United States)"/>
<marker lat="40.433" lon="-79.983" site="Pittsburgh (Pennsylvania, United States)"/>
<marker lat="36.25" lon="-83.83" site="Bull's Gap (Tennessee, United States)"/>
<marker lat="35.5" lon="-85.0" site="Tennessee (Tennessee, United States)"/>
<marker lat="38.5" lon="-78.616" site="Page Valley (Virginia, United States)"/>
<marker lat="37.0" lon="-80.0" site="Virginia (Virginia, United States)"/>
<marker lat="34.883" lon="-82.366" site="Greenville county (South Carolina, United States)"/>
<marker lat="35.35" lon="-86.2" site="Tullahoma (Tennessee, United States)"/>
<marker lat="46.0" lon="2.0" site="France (France)"/>
<marker lat="37.733" lon="-77.916" site="Goochland (Virginia, United States)"/>
<marker lat="36.916" lon="-80.4" site="Floyd (Virginia, United States)"/>
<marker lat="38.5" lon="-77.966" site="Culpeper (Virginia, United States)"/>
</markers>