<markers>
<marker lat="37.9667" lon="23.7333" site="Athens (Greece)"/>
<marker lat="39.0" lon="22.0" site="Greece (Greece)"/>
<marker lat="32.0" lon="53.0" site="Persia (Iran)"/>
<marker lat="38.566" lon="23.833" site="Euboea (Greece)"/>
<marker lat="40.825" lon="23.8583" site="Amphipolis (Greece)"/>
<marker lat="39.5" lon="22.25" site="Thessaly (Greece)"/>
<marker lat="38.325" lon="23.3333" site="Thebes (Greece)"/>
<marker lat="34.766" lon="48.583" site="Ecbatana (Iran)"/>
<marker lat="40.3" lon="23.3667" site="Olynthus"/>
<marker lat="38.83" lon="23.5" site="Attica (Greece)"/>
<marker lat="38.8" lon="22.5583" site="Thermopylae"/>
<marker lat="38.0" lon="23.35" site="Megara (Greece)"/>
<marker lat="27.0" lon="30.0" site="Egypt (Egypt)"/>
<marker lat="41.333" lon="26.75" site="Thrace (Greece)"/>
<marker lat="37.6417" lon="22.7333" site="Argos (Greece)"/>
<marker lat="42.5" lon="26.5" site="Cabyle (Bulgaria)"/>
<marker lat="37.8833" lon="21.4" site="Elis (Greece)"/>
<marker lat="39.05" lon="26.95" site="Atarneus"/>
<marker lat="36.666" lon="27.366" site="Cnidus (Turkey)"/>
<marker lat="41.833" lon="22.0" site="Macedonia (Macedonia)"/>
<marker lat="32.2" lon="48.333" site="Susa (Iran)"/>
<marker lat="39.15" lon="20.9833" site="Ambracia (Greece)"/>
</markers>