<markers>
<marker lat="32.35" lon="-90.866" site="Vicksburg (Mississippi, United States)"/>
<marker lat="35.33" lon="-85.3" site="Chattanooga (Tennessee, United States)"/>
<marker lat="39.816" lon="-77.216" site="Gettysburg (Pennsylvania, United States)"/>
<marker lat="38.3" lon="-77.45" site="Fredericksburg, Va. (Virginia, United States)"/>
<marker lat="38.3" lon="-77.633" site="Chancellorsville (Virginia, United States)"/>
<marker lat="32.283" lon="-90.183" site="Jackson (Mississippi, United States)"/>
<marker lat="35.5" lon="-85.0" site="Tennessee (Tennessee, United States)"/>
<marker lat="35.95" lon="-83.916" site="Knoxville (Tennessee, United States)"/>
<marker lat="37.0" lon="-85.0" site="Kentucky (Kentucky, United States)"/>
<marker lat="35.95" lon="-87.366" site="Missionary Ridge, Tenn. (Tennessee, United States)"/>
<marker lat="38.883" lon="-77.33" site="Washington (United States)"/>
<marker lat="36.166" lon="-86.75" site="Edgefield (Tennessee, United States)"/>
<marker lat="39.7" lon="-77.316" site="Emmitsburg (Maryland, United States)"/>
<marker lat="38.25" lon="-85.75" site="Louisville (Kentucky, United States)"/>
<marker lat="33.0" lon="-90.0" site="Mississippi (Mississippi, United States)"/>
<marker lat="35.0" lon="-93.0" site="Arkansas (Arkansas, United States)"/>
<marker lat="30.666" lon="-91.266" site="Port Hudson (Louisiana, United States)"/>
<marker lat="37.65" lon="-84.95" site="Perryville (Kentucky, United States)"/>
<marker lat="35.833" lon="-86.383" site="Murfreesboro (Tennessee, United States)"/>
<marker lat="34.983" lon="-85.333" site="Lookout Mountain, Tenn. (Tennessee, United States)"/>
<marker lat="32.16" lon="-91.5" site="Grand Gulf (Mississippi, United States)"/>
<marker lat="41.566" lon="-77.233" site="Plank (Pennsylvania, United States)"/>
<marker lat="35.95" lon="-83.116" site="Bridgeport, Tennessee (Tennessee, United States)"/>
<marker lat="39.816" lon="-77.216" site="Cemetery Hill (Pennsylvania, United States)"/>
<marker lat="32.35" lon="-90.533" site="Champion's Hill (Mississippi, United States)"/>
<marker lat="35.133" lon="-90.33" site="Memphis (Tennessee, United States)"/>
<marker lat="38.0" lon="-98.0" site="United States (United States)"/>
<marker lat="39.816" lon="-77.216" site="Culp's Hill (Pennsylvania, United States)"/>
<marker lat="31.95" lon="-90.983" site="Port Gibson (Mississippi, United States)"/>
<marker lat="37.66" lon="-88.55" site="Tennessee River (United States)"/>
<marker lat="36.583" lon="-83.666" site="Cumberland Gap (Tennessee, United States)"/>
<marker lat="45.766" lon="-116.8" site="Cemetery Ridge (Oregon, United States)"/>
<marker lat="33.533" lon="-90.166" site="Yazoo River (United States)"/>
<marker lat="38.0" lon="-98.0" site="Missouri (Missouri, United States)"/>
<marker lat="40.833" lon="-76.0" site="Pennsylvania (Pennsylvania, United States)"/>
<marker lat="44.466" lon="-91.533" site="Lookout Valley (Wisconsin, United States)"/>
<marker lat="39.933" lon="-77.65" site="Chambersburg, Pa. (Pennsylvania, United States)"/>
<marker lat="34.933" lon="-88.516" site="Corinth (Mississippi, United States)"/>
<marker lat="34.966" lon="-85.283" site="Rossville (Georgia, United States)"/>
<marker lat="38.3" lon="-77.65" site="Hazel Grove (Virginia, United States)"/>
<marker lat="32.25" lon="-90.416" site="Raymond (Mississippi, United States)"/>
<marker lat="34.733" lon="-92.283" site="Little Rock (Arkansas, United States)"/>
<marker lat="37.266" lon="-85.883" site="Munfordville (Kentucky, United States)"/>
<marker lat="39.816" lon="-77.233" site="Seminary Ridge (Pennsylvania, United States)"/>
<marker lat="35.983" lon="-86.45" site="Stone River (Tennessee, United States)"/>
<marker lat="30.45" lon="-91.15" site="Baton Rouge (Louisiana, United States)"/>
<marker lat="38.316" lon="-77.466" site="Falmouth, Va. (Virginia, United States)"/>
<marker lat="39.316" lon="-77.733" site="Harper's Ferry (West Virginia, United States)"/>
<marker lat="38.7" lon="-77.783" site="Warrenton (Virginia, United States)"/>
<marker lat="38.2" lon="-84.866" site="Frankfort (Kentucky, United States)"/>
<marker lat="36.666" lon="-76.916" site="Franklin, Va. (Virginia, United States)"/>
<marker lat="34.483" lon="-90.6" site="Helena, Ark. (Arkansas, United States)"/>
<marker lat="39.65" lon="-77.166" site="Taneytown (Maryland, United States)"/>
<marker lat="35.35" lon="-86.2" site="Tullahoma (Tennessee, United States)"/>
<marker lat="39.6" lon="-77.816" site="Williamsport (Maryland, United States)"/>
<marker lat="39.866" lon="-77.733" site="Cashtown (Pennsylvania, United States)"/>
<marker lat="34.866" lon="-85.833" site="Stevenson (Alabama, United States)"/>
<marker lat="39.0" lon="-76.833" site="Maryland (Maryland, United States)"/>
<marker lat="39.183" lon="-78.15" site="Winchester, Va. (Virginia, United States)"/>
<marker lat="33.0" lon="-87.0" site="Alabama (Alabama, United States)"/>
<marker lat="37.33" lon="-89.183" site="Cairo, Ill. (Illinois, United States)"/>
<marker lat="37.8" lon="-85.466" site="Bardstown (Kentucky, United States)"/>
<marker lat="31.0" lon="-92.0" site="Louisiana (Louisiana, United States)"/>
<marker lat="39.15" lon="-84.45" site="Cincinnati (Ohio, United States)"/>
<marker lat="39.783" lon="-77.366" site="Fairfield, Pa. (Pennsylvania, United States)"/>
<marker lat="38.866" lon="-78.1" site="Rappahannock (Virginia, United States)"/>
<marker lat="38.283" lon="-77.466" site="Marye's Heights (Virginia, United States)"/>
<marker lat="39.283" lon="-76.6" site="Baltimore, Md. (Maryland, United States)"/>
<marker lat="39.8" lon="-76.983" site="McAllister (Pennsylvania, United States)"/>
<marker lat="40.266" lon="-76.883" site="Harrisburg, Pa. (Pennsylvania, United States)"/>
<marker lat="39.566" lon="-76.983" site="Westminster (Maryland, United States)"/>
<marker lat="32.85" lon="-90.4" site="Yazoo City (Mississippi, United States)"/>
<marker lat="32.0" lon="-84.0" site="Georgia (Georgia, United States)"/>
<marker lat="38.466" lon="-77.983" site="Culpeper, Va. (Virginia, United States)"/>
<marker lat="32.66" lon="-99.83" site="Red River (Texas, United States)"/>
<marker lat="33.95" lon="-91.66" site="White River (Arkansas, United States)"/>
<marker lat="35.33" lon="-85.266" site="Orchard Knob (Tennessee, United States)"/>
<marker lat="36.983" lon="-86.433" site="Bowling Green (Kentucky, United States)"/>
<marker lat="35.683" lon="-85.766" site="McMinnville (Tennessee, United States)"/>
<marker lat="40.0" lon="-86.0" site="Indiana (Indiana, United States)"/>
<marker lat="32.45" lon="-91.1" site="Milliken's Bend (Louisiana, United States)"/>
<marker lat="37.55" lon="-77.45" site="Richmond (Virginia, United States)"/>
<marker lat="31.933" lon="-91.15" site="Bruinsburg (Mississippi, United States)"/>
<marker lat="30.0" lon="-100.0" site="Texas (Texas, United States)"/>
<marker lat="39.633" lon="-77.716" site="Hagerstown (Maryland, United States)"/>
<marker lat="32.766" lon="-108.616" site="Telegraph (New Mexico, United States)"/>
<marker lat="37.75" lon="-84.833" site="Harrodsburg (Kentucky, United States)"/>
<marker lat="34.9" lon="-85.1" site="Ringgold, Ga. (Georgia, United States)"/>
<marker lat="38.5" lon="-77.883" site="Brandy Station (Virginia, United States)"/>
<marker lat="36.2" lon="-86.283" site="Lebanon (Tennessee, United States)"/>
<marker lat="32.333" lon="-90.316" site="Clinton (Mississippi, United States)"/>
<marker lat="34.25" lon="-88.7" site="Tupelo (Mississippi, United States)"/>
<marker lat="34.75" lon="-85.4" site="Chattanooga Valley (United States)"/>
<marker lat="39.45" lon="-77.95" site="Martinsburg (West Virginia, United States)"/>
<marker lat="32.283" lon="-90.283" site="Bakers Creek (Mississippi, United States)"/>
<marker lat="39.4" lon="-77.4" site="Frederick, Md. (Maryland, United States)"/>
<marker lat="38.483" lon="-78.2" site="Deep Run (Virginia, United States)"/>
<marker lat="38.966" lon="-77.633" site="Aldie (Virginia, United States)"/>
<marker lat="39.9" lon="-89.933" site="Rock Creek, Menard County, Illinois (Illinois, United States)"/>
<marker lat="37.2" lon="-93.283" site="Springfield, Mo. (Missouri, United States)"/>
<marker lat="33.683" lon="-89.116" site="Big Black (Mississippi, United States)"/>
<marker lat="47.233" lon="-95.2" site="Mississippi (United States)"/>
<marker lat="38.133" lon="-78.183" site="Gordonsville (Virginia, United States)"/>
<marker lat="35.716" lon="-84.333" site="Loudon, Tenn. (Tennessee, United States)"/>
<marker lat="36.983" lon="-89.133" site="Ohio (United States)"/>
<marker lat="38.833" lon="-77.416" site="Centreville (Virginia, United States)"/>
<marker lat="30.683" lon="-88.33" site="Mobile, Ala. (Alabama, United States)"/>
<marker lat="35.483" lon="-86.45" site="Shelbyville, Tenn. (Tennessee, United States)"/>
<marker lat="39.216" lon="-78.25" site="Frederick (Virginia, United States)"/>
<marker lat="38.466" lon="-77.766" site="Kelly's Ford (Virginia, United States)"/>
<marker lat="38.616" lon="-90.183" site="St. Louis (Missouri, United States)"/>
<marker lat="39.883" lon="-77.233" site="Willoughby Run (Pennsylvania, United States)"/>
<marker lat="34.816" lon="-85.4" site="Chattanooga Creek (United States)"/>
<marker lat="37.583" lon="-77.1" site="Tunstall (Virginia, United States)"/>
<marker lat="34.716" lon="-86.583" site="Huntsville (Alabama, United States)"/>
<marker lat="32.766" lon="-79.916" site="Charleston (South Carolina, United States)"/>
<marker lat="34.633" lon="-85.383" site="Pigeon Mountain (Georgia, United States)"/>
<marker lat="34.766" lon="-89.433" site="Holly Springs (Mississippi, United States)"/>
<marker lat="33.733" lon="-84.383" site="Atlanta (Georgia, United States)"/>
<marker lat="33.5" lon="-90.166" site="Greenwood (Mississippi, United States)"/>
<marker lat="37.633" lon="-84.766" site="Danville, Ky. (Kentucky, United States)"/>
<marker lat="33.766" lon="-89.8" site="Grenada (Mississippi, United States)"/>
<marker lat="38.283" lon="-77.466" site="Lee's Hill (Virginia, United States)"/>
<marker lat="38.133" lon="-79.66" site="Staunton, Va. (Virginia, United States)"/>
<marker lat="32.4" lon="-90.833" site="Chickasaw Bayou (Mississippi, United States)"/>
<marker lat="35.2" lon="-85.833" site="Battle Creek (Tennessee, United States)"/>
<marker lat="33.466" lon="-82.16" site="Augusta (Georgia, United States)"/>
<marker lat="35.966" lon="-83.9" site="Temperance Hill (Tennessee, United States)"/>
<marker lat="34.45" lon="-85.483" site="Alpine, Ga. (Georgia, United States)"/>
<marker lat="35.783" lon="-84.25" site="Lenoirs (Tennessee, United States)"/>
<marker lat="37.933" lon="-82.6" site="Peach Orchard (Kentucky, United States)"/>
<marker lat="31.75" lon="-93.83" site="Natchitoches (Louisiana, United States)"/>
<marker lat="36.983" lon="-85.9" site="Glasgow, Ky. (Kentucky, United States)"/>
<marker lat="38.416" lon="-77.4" site="Stafford Court House (Virginia, United States)"/>
<marker lat="39.7" lon="-79.666" site="Hazel Run (West Virginia, United States)"/>
<marker lat="34.933" lon="-85.283" site="Fairview (Georgia, United States)"/>
<marker lat="35.466" lon="-86.83" site="Manchester, Tenn. (Tennessee, United States)"/>
<marker lat="35.1" lon="-88.35" site="Shiloh, Tenn. (Tennessee, United States)"/>
<marker lat="35.33" lon="-85.5" site="Raccoon Mountains (Tennessee, United States)"/>
<marker lat="36.383" lon="-86.433" site="Gallatin, Tenn. (Tennessee, United States)"/>
<marker lat="40.0" lon="-80.833" site="Ohio (Ohio, United States)"/>
<marker lat="35.5" lon="-80.0" site="North Carolina (North Carolina, United States)"/>
<marker lat="39.0" lon="-80.0" site="West Virginia (West Virginia, United States)"/>
<marker lat="32.333" lon="-90.45" site="Bolton's Depot (Mississippi, United States)"/>
<marker lat="38.2" lon="-77.583" site="Spottsylvania (Virginia, United States)"/>
<marker lat="34.516" lon="-85.35" site="Dry Valley (Georgia, United States)"/>
<marker lat="35.5" lon="-84.783" site="Decatur (Tennessee, United States)"/>
<marker lat="29.7" lon="-91.216" site="Berwick Bay (Louisiana, United States)"/>
<marker lat="34.433" lon="-90.483" site="Yazoo Pass (Mississippi, United States)"/>
<marker lat="39.95" lon="-76.716" site="York, Pa. (Pennsylvania, United States)"/>
<marker lat="32.383" lon="-90.866" site="McNutt Lake (Mississippi, United States)"/>
<marker lat="35.966" lon="-88.933" site="Trenton, Tenn. (Tennessee, United States)"/>
<marker lat="40.2" lon="-77.183" site="Carlisle, Pa. (Pennsylvania, United States)"/>
<marker lat="33.116" lon="-90.95" site="Steele's Bayou (Mississippi, United States)"/>
<marker lat="38.8" lon="-77.33" site="Alexandria (Virginia, United States)"/>
<marker lat="37.583" lon="-84.883" site="Chaplin (Kentucky, United States)"/>
<marker lat="40.0" lon="-89.0" site="Illinois (Illinois, United States)"/>
<marker lat="35.0" lon="-98.0" site="Oklahoma (Oklahoma, United States)"/>
<marker lat="39.55" lon="-77.883" site="Falling Waters (West Virginia, United States)"/>
<marker lat="39.333" lon="-77.716" site="Maryland Heights (Maryland, United States)"/>
<marker lat="35.66" lon="-85.25" site="Citico Creek (Tennessee, United States)"/>
<marker lat="34.766" lon="-84.966" site="Dalton, Ga. (Georgia, United States)"/>
<marker lat="39.0" lon="-105.0" site="Colorado (Colorado, United States)"/>
<marker lat="41.366" lon="-83.65" site="Bowling Green, Wood County, Ohio (Ohio, United States)"/>
<marker lat="37.733" lon="-85.66" site="Mackville (Kentucky, United States)"/>
<marker lat="35.883" lon="-84.166" site="Station West (Tennessee, United States)"/>
<marker lat="38.5" lon="-83.933" site="Mount Sterling, Ky. (Kentucky, United States)"/>
<marker lat="35.866" lon="-84.5" site="Kingston (Tennessee, United States)"/>
<marker lat="36.383" lon="-86.166" site="Hartsville (Tennessee, United States)"/>
<marker lat="39.566" lon="-77.95" site="Georgetown (West Virginia, United States)"/>
<marker lat="37.683" lon="-84.65" site="Camp Dick Robinson (Kentucky, United States)"/>
<marker lat="29.733" lon="-93.883" site="Sabine Pass (Texas, United States)"/>
<marker lat="41.85" lon="-87.65" site="Chicago (Illinois, United States)"/>
<marker lat="39.83" lon="-84.5" site="Covington (Kentucky, United States)"/>
<marker lat="36.483" lon="-87.85" site="Fort Donelson (Tennessee, United States)"/>
<marker lat="40.633" lon="-90.15" site="Fairview, Ill. (Illinois, United States)"/>
<marker lat="35.416" lon="-85.716" site="Altamont (Tennessee, United States)"/>
<marker lat="37.1" lon="-82.716" site="Cumberland River (Kentucky, United States)"/>
<marker lat="38.666" lon="-98.0" site="Kansas (Kansas, United States)"/>
<marker lat="38.483" lon="-78.416" site="Rapidan (Virginia, United States)"/>
<marker lat="33.933" lon="-88.9" site="Chickasaw (Mississippi, United States)"/>
<marker lat="34.366" lon="-91.133" site="St. Charles, Ark. (Arkansas, United States)"/>
<marker lat="35.666" lon="-92.733" site="Arkansas (United States)"/>
<marker lat="32.366" lon="-86.3" site="Montgomery (Alabama, United States)"/>
<marker lat="34.433" lon="-89.766" site="Moccasin Point (Mississippi, United States)"/>
<marker lat="36.0" lon="-86.566" site="Lavergne (Tennessee, United States)"/>
<marker lat="39.5" lon="-77.65" site="Boonsboro (Maryland, United States)"/>
<marker lat="38.433" lon="-77.9" site="Stevensburg (Virginia, United States)"/>
<marker lat="38.55" lon="-117.483" site="Mississippi Springs (Nevada, United States)"/>
<marker lat="41.166" lon="-73.2" site="Bridgeport (Connecticut, United States)"/>
<marker lat="32.866" lon="-85.183" site="West Point (Georgia, United States)"/>
<marker lat="39.65" lon="-78.75" site="Cumberland (Maryland, United States)"/>
<marker lat="39.883" lon="-77.283" site="Mummasburg (Pennsylvania, United States)"/>
<marker lat="36.716" lon="-76.583" site="Suffolk, Va. (Virginia, United States)"/>
<marker lat="37.9" lon="-86.233" site="Haysville (Kentucky, United States)"/>
<marker lat="35.2" lon="-86.66" site="Decherd (Tennessee, United States)"/>
<marker lat="35.433" lon="-94.333" site="Van Buren, Ark. (Arkansas, United States)"/>
<marker lat="30.1" lon="-90.983" site="Donaldsonville (Louisiana, United States)"/>
<marker lat="35.6" lon="-84.45" site="Sweetwater (Tennessee, United States)"/>
<marker lat="43.1" lon="-75.216" site="Utica (New York, United States)"/>
</markers>