<markers>
<marker lat="37.55" lon="-77.45" site="Richmond (Virginia, United States)"/>
<marker lat="37.316" lon="-77.266" site="City Point (Virginia, United States)"/>
<marker lat="32.283" lon="-90.183" site="Jackson (Mississippi, United States)"/>
<marker lat="37.333" lon="-77.25" site="Shirley (Virginia, United States)"/>
<marker lat="36.966" lon="-76.35" site="Hampton Roads (Virginia, United States)"/>
<marker lat="37.516" lon="-76.783" site="West Point (Virginia, United States)"/>
<marker lat="38.5" lon="-82.416" site="Quaker (West Virginia, United States)"/>
<marker lat="37.7" lon="-77.616" site="Chickahominy (Virginia, United States)"/>
<marker lat="40.833" lon="-76.0" site="Pennsylvania (Pennsylvania, United States)"/>
<marker lat="34.766" lon="-89.433" site="Holly Springs (Mississippi, United States)"/>
<marker lat="37.516" lon="-76.783" site="York (Virginia, United States)"/>
<marker lat="37.5" lon="-77.3" site="White Oak Swamp (Virginia, United States)"/>
<marker lat="38.283" lon="-78.8" site="Port Republic (Virginia, United States)"/>
<marker lat="37.333" lon="-77.66" site="Charles City (Virginia, United States)"/>
<marker lat="30.566" lon="-81.683" site="Nassau River (Florida, United States)"/>
<marker lat="35.0" lon="-93.0" site="Arkansas (Arkansas, United States)"/>
<marker lat="39.45" lon="-78.33" site="Berkeley County (West Virginia, United States)"/>
<marker lat="38.566" lon="-76.166" site="Hudson River (Maryland, United States)"/>
<marker lat="37.8" lon="-77.4" site="Pamunkey (Virginia, United States)"/>
<marker lat="33.0" lon="-87.0" site="Alabama (Alabama, United States)"/>
<marker lat="37.3" lon="-78.383" site="Farmville (Virginia, United States)"/>
<marker lat="36.616" lon="-78.666" site="White House (Virginia, United States)"/>
<marker lat="40.683" lon="-75.216" site="Easton, Pa. (Pennsylvania, United States)"/>
<marker lat="32.216" lon="-80.666" site="Hilton Head (South Carolina, United States)"/>
<marker lat="38.983" lon="-96.666" site="Geary (Kansas, United States)"/>
<marker lat="34.25" lon="-85.15" site="Rome, Ga. (Georgia, United States)"/>
<marker lat="37.466" lon="-77.783" site="Turkey Creek (Virginia, United States)"/>
<marker lat="37.3" lon="-77.15" site="Westover (Virginia, United States)"/>
<marker lat="37.35" lon="-77.25" site="Turkey Bend (Virginia, United States)"/>
<marker lat="36.683" lon="-83.1" site="Jonesville (Virginia, United States)"/>
<marker lat="29.2" lon="-83.66" site="Shell Mound (Florida, United States)"/>
<marker lat="40.0" lon="-89.0" site="Illinois (Illinois, United States)"/>
<marker lat="37.766" lon="-79.383" site="South River (Virginia, United States)"/>
<marker lat="34.0" lon="-80.0" site="South Carolina (South Carolina, United States)"/>
<marker lat="38.85" lon="-76.616" site="Harwood (Maryland, United States)"/>
<marker lat="35.95" lon="-83.916" site="Knoxville (Tennessee, United States)"/>
<marker lat="41.383" lon="-84.116" site="Napoleon (Ohio, United States)"/>
<marker lat="35.683" lon="-75.716" site="Old Point (North Carolina, United States)"/>
<marker lat="32.7" lon="-79.933" site="Secessionville (South Carolina, United States)"/>
<marker lat="45.0" lon="-90.0" site="Wisconsin (Wisconsin, United States)"/>
<marker lat="37.0" lon="-80.0" site="Virginia (Virginia, United States)"/>
<marker lat="42.9" lon="-77.733" site="Avon, N. Y. (New York, United States)"/>
<marker lat="36.583" lon="-83.666" site="Cumberland Gap (Tennessee, United States)"/>
<marker lat="38.6" lon="-75.133" site="White House Point (Delaware, United States)"/>
<marker lat="35.216" lon="-80.833" site="Charlotte (North Carolina, United States)"/>
<marker lat="30.733" lon="-89.483" site="Savannah (Mississippi, United States)"/>
<marker lat="34.466" lon="-85.7" site="Will's Valley (Alabama, United States)"/>
<marker lat="36.7" lon="-78.35" site="Mecklenburg (Virginia, United States)"/>
<marker lat="36.683" lon="-83.133" site="Lee County, Va. (Virginia, United States)"/>
</markers>